jsons/__init__.py
jsons/_cache.py
jsons/_common_impl.py
jsons/_compatibility_impl.py
jsons/_datetime_impl.py
jsons/_dump_impl.py
jsons/_extra_impl.py
jsons/_fork_impl.py
jsons/_key_transformers.py
jsons/_lizers_impl.py
jsons/_load_impl.py
jsons/_multitasking.py
jsons/_package_info.py
jsons/_transform_impl.py
jsons/_validation.py
jsons/decorators.py
jsons/exceptions.py
jsons/classes/__init__.py
jsons/classes/json_serializable.py
jsons/classes/verbosity.py
jsons/deserializers/__init__.py
jsons/deserializers/default_complex.py
jsons/deserializers/default_date.py
jsons/deserializers/default_datetime.py
jsons/deserializers/default_decimal.py
jsons/deserializers/default_defaultdict.py
jsons/deserializers/default_dict.py
jsons/deserializers/default_enum.py
jsons/deserializers/default_iterable.py
jsons/deserializers/default_list.py
jsons/deserializers/default_mapping.py
jsons/deserializers/default_nonetype.py
jsons/deserializers/default_object.py
jsons/deserializers/default_path.py
jsons/deserializers/default_primitive.py
jsons/deserializers/default_string.py
jsons/deserializers/default_time.py
jsons/deserializers/default_timedelta.py
jsons/deserializers/default_timezone.py
jsons/deserializers/default_tuple.py
jsons/deserializers/default_union.py
jsons/deserializers/default_uuid.py
jsons/deserializers/default_zone_info.py
jsons/serializers/__init__.py
jsons/serializers/default_complex.py
jsons/serializers/default_date.py
jsons/serializers/default_datetime.py
jsons/serializers/default_decimal.py
jsons/serializers/default_dict.py
jsons/serializers/default_enum.py
jsons/serializers/default_iterable.py
jsons/serializers/default_list.py
jsons/serializers/default_object.py
jsons/serializers/default_path.py
jsons/serializers/default_primitive.py
jsons/serializers/default_time.py
jsons/serializers/default_timedelta.py
jsons/serializers/default_timezone.py
jsons/serializers/default_tuple.py
jsons/serializers/default_union.py
jsons/serializers/default_uuid.py
jsons-1.6.3.dist-info/LICENSE
jsons-1.6.3.dist-info/METADATA
jsons-1.6.3.dist-info/WHEEL
jsons-1.6.3.dist-info/top_level.txt
jsons-1.6.3.dist-info/RECORD
