Metadata-Version: 2.1
Name: jsons
Version: 1.6.3
Summary: For serializing Python objects to JSON (dicts) and back
Home-page: https://github.com/ramonhagenaars/jsons
Author: Ramon Hagenaars
Author-email: ramon.hagenaars@gmail.com
License: MIT
Platform: UNKNOWN
Classifier: Intended Audience :: Developers
Classifier: License :: OSI Approved :: MIT License
Classifier: Operating System :: OS Independent
Classifier: Natural Language :: English
Classifier: Programming Language :: Python
Classifier: Programming Language :: Python :: 3
Classifier: Programming Language :: Python :: 3.5
Classifier: Programming Language :: Python :: 3.6
Classifier: Programming Language :: Python :: 3.7
Classifier: Programming Language :: Python :: 3.8
Classifier: Programming Language :: Python :: 3.9
Classifier: Programming Language :: Python :: 3.10
Requires-Python: >=3.5
Provides-Extra: test
